hacktools/psp.py
hacktools/compression.py
hacktools/cmp_racjin.cpython-311-x86_64-linux-gnu.so
hacktools/cmp_lzss.cpython-311-x86_64-linux-gnu.so
hacktools/nasm.py
hacktools/psx.py
hacktools/nds.py
hacktools/arch.py
hacktools/cmp_cri.cpython-311-x86_64-linux-gnu.so
hacktools/__init__.py
hacktools/cpk.py
hacktools/gb.py
hacktools/wii.py
hacktools/cmp_misc.cpython-311-x86_64-linux-gnu.so
hacktools/ws.py
hacktools/gui.py
hacktools/common.py
hacktools/nitro.py
hacktools/assets/icon.png
hacktools-0.38.6.dist-info/METADATA
hacktools-0.38.6.dist-info/LICENSE
hacktools-0.38.6.dist-info/top_level.txt
hacktools-0.38.6.dist-info/WHEEL
hacktools-0.38.6.dist-info/RECORD
