Metadata-Version: 2.4
Name: hacktools
Version: 0.38.6
Summary: A set of utilities and tools for rom hacking and translations.
Home-page: https://github.com/Illidanz/hacktools
Author: Illidan
Classifier: Programming Language :: Python :: 3.7
Classifier: Programming Language :: Python :: 3.8
Classifier: Programming Language :: Python :: 3.9
Classifier: Programming Language :: Python :: 3.10
Classifier: Programming Language :: Python :: 3.11
Classifier: Programming Language :: Python :: 3.12
Classifier: Programming Language :: Python :: 3.13
Classifier: License :: OSI Approved :: MIT License
Classifier: Operating System :: OS Independent
Requires-Python: >=3.7
License-File: LICENSE
Provides-Extra: nds
Requires-Dist: ndspy; extra == "nds"
Provides-Extra: armips
Requires-Dist: pyarmips; extra == "armips"
Provides-Extra: xdelta
Requires-Dist: pyxdelta; extra == "xdelta"
Provides-Extra: iso
Requires-Dist: pymkpsxiso; extra == "iso"
Provides-Extra: psp
Requires-Dist: pycdlib; extra == "psp"
Requires-Dist: pyeboot; extra == "psp"
Provides-Extra: ips
Requires-Dist: ips_util; extra == "ips"
Provides-Extra: graphics
Requires-Dist: Pillow; extra == "graphics"
Provides-Extra: cli
Requires-Dist: click; extra == "cli"
Requires-Dist: tqdm; extra == "cli"
Requires-Dist: customtkinter; extra == "cli"
Provides-Extra: all
Requires-Dist: ndspy; extra == "all"
Requires-Dist: pyarmips; extra == "all"
Requires-Dist: pyxdelta; extra == "all"
Requires-Dist: pymkpsxiso; extra == "all"
Requires-Dist: pycdlib; extra == "all"
Requires-Dist: pyeboot; extra == "all"
Requires-Dist: ips_util; extra == "all"
Requires-Dist: Pillow; extra == "all"
Requires-Dist: click; extra == "all"
Requires-Dist: tqdm; extra == "all"
Requires-Dist: customtkinter; extra == "all"
Dynamic: author
Dynamic: classifier
Dynamic: description
Dynamic: description-content-type
Dynamic: home-page
Dynamic: license-file
Dynamic: provides-extra
Dynamic: requires-python
Dynamic: summary
